{
  "1": "https://s3u.intelligentinfrastructure.space/v4/k5/8kc8rw/cf-master.1777275406.txt",
  "2": "https://syd.goldenridgeproductionworks.space/v4/hld/3g93e6/cf-master.1777272823.txt",
  "3": "https://s3u.stellarpathcreative.space/v4/s93/dnftmv/cf-master.1775467777.txt",
  "4": "https://syd.novaquestmedical.space/v4/sc/bf3btd/cf-master.1777275113.txt",
  "5": "https://sbi.claravonventures.space/v4/sc/fdgflk/cf-master.1777272890.txt",
  "6": "https://sw5.brightluneagency.cyou/v4/3vi/qykq9s/cf-master.1777273074.txt",
  "7": "https://s3u.halcyoninnovation.cfd/v4/ox/1cf1pt/cf-master.1777273054.txt",
  "8": "https://sbi.strategicexecution.sbs/v4/qu/qynixv/cf-master.1775465785.txt",
  "9": "https://syd.claravonfinancial.cfd/v4/9a/fugnt/cf-master.1751605561.txt",
  "10": "https://s3u.halcyoncreative.site/v4/bgm/qjkt9/cf-master.1751608712.txt",
  "11": "https://sw5.clarionwellbeing.cfd/v4/vz1/bx3du/cf-master.1751608690.txt",
  "12": "https://sxd.aurorapathmedia.space/v4/db/6ebcl/cf-master.1751605666.txt",
  "13": "https://sxd.clarionpathlab.site/v4/pp/1afmr/cf-master.1751608550.txt",
  "14": "https://sbi.clarionedgeventures.sbs/v4/gee/ozquf/cf-master.1751605703.txt",
  "15": "https://s3u.auroriontravel.shop/v4/5c/fugn5/cf-master.1751608531.txt",
  "16": "https://syd.marketmicrostructure.cfd/v4/hz/61bb1c/cf-master.1777221496.txt"
}