{
  "1": "https://sbi.sunrisevalleyproductionworks.store/v4/db/9gwpew/cf-master.1779895805.txt",
  "2": "https://syd.clarionquestdigital.site/v4/5c/ckh35e/cf-master.1779897657.txt",
  "3": "https://syd.aurorionventures.shop/v4/5c/kytf9s/cf-master.1779895592.txt",
  "4": "https://syd.auroriaconsulting.cyou/v4/hz/nox6jp/cf-master.1779895895.txt",
  "5": "https://s5zt.mindspireeducation.cyou/v4/x6b/d36uod/cf-master.1779895925.txt",
  "6": "https://s3wh.skylineinnovationhub.site/v4/x6b/3198cq/cf-master.1779895830.txt"
}