{
  "1": "https://s3u.aurorafieldagency.shop/v4/m9/gw31is/cf-master.1775219730.txt",
  "2": "https://s3u.sunrisefieldcreativeworks.store/v4/61/asepvq/cf-master.1775207361.txt",
  "3": "https://sw5.organicgoods.cfd/v4/3vi/96vt9o/cf-master.1775672028.txt",
  "4": "https://sbi.personalplatform.cyou/v4/vz/3gj6dt/cf-master.1775207280.txt",
  "5": "https://sw5.personalplatform.cyou/v4/tab/tlyar1/cf-master.1775208243.txt",
  "6": "https://sw5.sunrisevalleyproductionworks.store/v4/k5/kh8our/cf-master.1775207740.txt",
  "7": "https://sbi.auralithproduction.space/v4/hld/nqdktr/cf-master.1775208389.txt"
}