{
  "1": "https://sbi.smartlifespace.shop/v4/c5u/616evc/cf-master.1777569578.txt",
  "2": "https://sbi.silverpathacademy.cyou/v4/61/bfbx5w/cf-master.1777572866.txt",
  "3": "https://sxd.mindspireventures.sbs/v4/lf/oxozcl/cf-master.1777569532.txt",
  "4": "https://sbi.clarionquestgroup.cfd/v4/61/1c1a9k/cf-master.1777569556.txt",
  "5": "https://sbi.auralithproduction.space/v4/61/fdfuzq/cf-master.1777572187.txt",
  "6": "https://sw5.stellarpathbranding.cyou/v4/ck/dndpbx/cf-master.1777571409.txt",
  "7": "https://sxd.halcyoninnovation.cfd/v4/61/khkvwb/cf-master.1777569919.txt",
  "8": "https://sw5.aurorapathmedia.space/v4/is3/mom51l/cf-master.1777572861.txt",
  "9": "https://syd.clarionquestgroup.cfd/v4/61/gwgtjx/cf-master.1777569788.txt",
  "10": "https://syd.novaquestbranding.cyou/v4/61/lilwy6/cf-master.1777569932.txt",
  "11": "https://sxd.novaqueststudio.cyou/v4/36/zbzosh/cf-master.1777569573.txt",
  "12": "https://syd.intelligentinfrastructure.space/v4/36/eae6kb/cf-master.1777569844.txt"
}