{
  "1156": "https://s3u.lakesideinnovationstudio.sbs/v4/vz/liu33l/cf-master.1776141436.txt",
  "1157": "https://sbi.aurorafabrication.space/v4/5w3/mo8aan/cf-master.1776141474.txt",
  "1158": "https://srcf.merridianproductions.store/v4/36/czf56a/cf-master.1776828414.txt",
  "1159": "https://s3u.claravonventures.space/v4/k5/khmkuz/cf-master.1777264141.txt",
  "1160": "https://sxd.aurorapathstudios.space/v4/c5u/dm8ytm/cf-master.1777830018.txt",
  "1161": "https://sw5.clarionquestacademy.cfd/v4/xy/qxxkj5/cf-master.1778739581.txt",
  "1162": "https://srcf.merridianproductions.store/v4/pk8/ikajfd/cf-master.1779713069.txt",
  "1163": "https://sknw.wanderpeakevents.store/v4/5w3/ocgwhw/cf-master.1779713144.txt",
  "1164": "",
  "1165": "",
  "1166": "",
  "1167": "",
  "1168": "",
  "1169": "",
  "1170": "",
  "1171": "",
  "1172": "",
  "1173": "",
  "1174": "",
  "1175": "",
  "1176": "",
  "1177": "",
  "1178": "",
  "1179": "",
  "1180": "",
  "1181": ""
}